simghg.py
simghg-0.1.2.dist-info/METADATA
simghg-0.1.2.dist-info/WHEEL
simghg-0.1.2.dist-info/entry_points.txt
simghg-0.1.2.dist-info/top_level.txt
simghg-0.1.2.dist-info/RECORD
