Metadata-Version: 2.1
Name: simghg
Version: 0.1.2
Summary: Package for N2O changing trends in each country in Annex.
Home-page: https://github.com/RyuseiDoi/ds_ad
Author: ryusei doi
Author-email: s2022048@stu.musashino-u.ac.jp
License: UNKNOWN
Project-URL: Bug Tracker, https://github.com/RyuseiDoi/ds_ad
Platform: UNKNOWN
Classifier: Programming Language :: Python :: 3
Classifier: License :: OSI Approved :: MIT License
Classifier: Operating System :: OS Independent
Requires-Python: >=3.7
